{"nodes": [{"id": "c_users_admin_desktop_travel_backend_src_services_activity_service_ts", "label": "activity.service.ts", "file_type": "code", "source_file": "C:\\Users\\Admin\\Desktop\\travel\\backend\\src\\services\\activity.service.ts", "source_location": "L1"}, {"id": "services_activity_service_activityservice", "label": "ActivityService", "file_type": "code", "source_file": "C:\\Users\\Admin\\Desktop\\travel\\backend\\src\\services\\activity.service.ts", "source_location": "L4"}, {"id": "services_activity_service_activityservice_list", "label": ".list()", "file_type": "code", "source_file": "C:\\Users\\Admin\\Desktop\\travel\\backend\\src\\services\\activity.service.ts", "source_location": "L5"}, {"id": "services_activity_service_activityservice_getbyid", "label": ".getById()", "file_type": "code", "source_file": "C:\\Users\\Admin\\Desktop\\travel\\backend\\src\\services\\activity.service.ts", "source_location": "L24"}, {"id": "services_activity_service_activityservice_create", "label": ".create()", "file_type": "code", "source_file": "C:\\Users\\Admin\\Desktop\\travel\\backend\\src\\services\\activity.service.ts", "source_location": "L34"}, {"id": "services_activity_service_activityservice_update", "label": ".update()", "file_type": "code", "source_file": "C:\\Users\\Admin\\Desktop\\travel\\backend\\src\\services\\activity.service.ts", "source_location": "L44"}, {"id": "services_activity_service_activityservice_delete", "label": ".delete()", "file_type": "code", "source_file": "C:\\Users\\Admin\\Desktop\\travel\\backend\\src\\services\\activity.service.ts", "source_location": "L55"}], "edges": [{"source": "c_users_admin_desktop_travel_backend_src_services_activity_service_ts", "target": "c_users_admin_desktop_travel_backend_src_config_supabase", "relation": "imports_from", "confidence": "EXTRACTED", "source_file": "C:\\Users\\Admin\\Desktop\\travel\\backend\\src\\services\\activity.service.ts", "source_location": "L1", "weight": 1.0}, {"source": "c_users_admin_desktop_travel_backend_src_services_activity_service_ts", "target": "c_users_admin_desktop_travel_backend_src_types", "relation": "imports_from", "confidence": "EXTRACTED", "source_file": "C:\\Users\\Admin\\Desktop\\travel\\backend\\src\\services\\activity.service.ts", "source_location": "L2", "weight": 1.0}, {"source": "c_users_admin_desktop_travel_backend_src_services_activity_service_ts", "target": "services_activity_service_activityservice", "relation": "contains", "confidence": "EXTRACTED", "source_file": "C:\\Users\\Admin\\Desktop\\travel\\backend\\src\\services\\activity.service.ts", "source_location": "L4", "weight": 1.0}, {"source": "services_activity_service_activityservice", "target": "services_activity_service_activityservice_list", "relation": "method", "confidence": "EXTRACTED", "source_file": "C:\\Users\\Admin\\Desktop\\travel\\backend\\src\\services\\activity.service.ts", "source_location": "L5", "weight": 1.0}, {"source": "services_activity_service_activityservice", "target": "services_activity_service_activityservice_getbyid", "relation": "method", "confidence": "EXTRACTED", "source_file": "C:\\Users\\Admin\\Desktop\\travel\\backend\\src\\services\\activity.service.ts", "source_location": "L24", "weight": 1.0}, {"source": "services_activity_service_activityservice", "target": "services_activity_service_activityservice_create", "relation": "method", "confidence": "EXTRACTED", "source_file": "C:\\Users\\Admin\\Desktop\\travel\\backend\\src\\services\\activity.service.ts", "source_location": "L34", "weight": 1.0}, {"source": "services_activity_service_activityservice", "target": "services_activity_service_activityservice_update", "relation": "method", "confidence": "EXTRACTED", "source_file": "C:\\Users\\Admin\\Desktop\\travel\\backend\\src\\services\\activity.service.ts", "source_location": "L44", "weight": 1.0}, {"source": "services_activity_service_activityservice", "target": "services_activity_service_activityservice_delete", "relation": "method", "confidence": "EXTRACTED", "source_file": "C:\\Users\\Admin\\Desktop\\travel\\backend\\src\\services\\activity.service.ts", "source_location": "L55", "weight": 1.0}], "raw_calls": [{"caller_nid": "services_activity_service_activityservice_list", "callee": "range", "is_member_call": true, "source_file": "C:\\Users\\Admin\\Desktop\\travel\\backend\\src\\services\\activity.service.ts", "source_location": "L9"}, {"caller_nid": "services_activity_service_activityservice_list", "callee": "order", "is_member_call": true, "source_file": "C:\\Users\\Admin\\Desktop\\travel\\backend\\src\\services\\activity.service.ts", "source_location": "L9"}, {"caller_nid": "services_activity_service_activityservice_list", "callee": "select", "is_member_call": true, "source_file": "C:\\Users\\Admin\\Desktop\\travel\\backend\\src\\services\\activity.service.ts", "source_location": "L9"}, {"caller_nid": "services_activity_service_activityservice_list", "callee": "from", "is_member_call": true, "source_file": "C:\\Users\\Admin\\Desktop\\travel\\backend\\src\\services\\activity.service.ts", "source_location": "L9"}, {"caller_nid": "services_activity_service_activityservice_list", "callee": "eq", "is_member_call": true, "source_file": "C:\\Users\\Admin\\Desktop\\travel\\backend\\src\\services\\activity.service.ts", "source_location": "L15"}, {"caller_nid": "services_activity_service_activityservice_list", "callee": "eq", "is_member_call": true, "source_file": "C:\\Users\\Admin\\Desktop\\travel\\backend\\src\\services\\activity.service.ts", "source_location": "L16"}, {"caller_nid": "services_activity_service_activityservice_list", "callee": "ilike", "is_member_call": true, "source_file": "C:\\Users\\Admin\\Desktop\\travel\\backend\\src\\services\\activity.service.ts", "source_location": "L17"}, {"caller_nid": "services_activity_service_activityservice_getbyid", "callee": "single", "is_member_call": true, "source_file": "C:\\Users\\Admin\\Desktop\\travel\\backend\\src\\services\\activity.service.ts", "source_location": "L25"}, {"caller_nid": "services_activity_service_activityservice_getbyid", "callee": "eq", "is_member_call": true, "source_file": "C:\\Users\\Admin\\Desktop\\travel\\backend\\src\\services\\activity.service.ts", "source_location": "L25"}, {"caller_nid": "services_activity_service_activityservice_getbyid", "callee": "select", "is_member_call": true, "source_file": "C:\\Users\\Admin\\Desktop\\travel\\backend\\src\\services\\activity.service.ts", "source_location": "L25"}, {"caller_nid": "services_activity_service_activityservice_getbyid", "callee": "from", "is_member_call": true, "source_file": "C:\\Users\\Admin\\Desktop\\travel\\backend\\src\\services\\activity.service.ts", "source_location": "L25"}, {"caller_nid": "services_activity_service_activityservice_create", "callee": "single", "is_member_call": true, "source_file": "C:\\Users\\Admin\\Desktop\\travel\\backend\\src\\services\\activity.service.ts", "source_location": "L35"}, {"caller_nid": "services_activity_service_activityservice_create", "callee": "select", "is_member_call": true, "source_file": "C:\\Users\\Admin\\Desktop\\travel\\backend\\src\\services\\activity.service.ts", "source_location": "L35"}, {"caller_nid": "services_activity_service_activityservice_create", "callee": "insert", "is_member_call": true, "source_file": "C:\\Users\\Admin\\Desktop\\travel\\backend\\src\\services\\activity.service.ts", "source_location": "L35"}, {"caller_nid": "services_activity_service_activityservice_create", "callee": "from", "is_member_call": true, "source_file": "C:\\Users\\Admin\\Desktop\\travel\\backend\\src\\services\\activity.service.ts", "source_location": "L35"}, {"caller_nid": "services_activity_service_activityservice_update", "callee": "single", "is_member_call": true, "source_file": "C:\\Users\\Admin\\Desktop\\travel\\backend\\src\\services\\activity.service.ts", "source_location": "L45"}, {"caller_nid": "services_activity_service_activityservice_update", "callee": "select", "is_member_call": true, "source_file": "C:\\Users\\Admin\\Desktop\\travel\\backend\\src\\services\\activity.service.ts", "source_location": "L45"}, {"caller_nid": "services_activity_service_activityservice_update", "callee": "eq", "is_member_call": true, "source_file": "C:\\Users\\Admin\\Desktop\\travel\\backend\\src\\services\\activity.service.ts", "source_location": "L45"}, {"caller_nid": "services_activity_service_activityservice_update", "callee": "from", "is_member_call": true, "source_file": "C:\\Users\\Admin\\Desktop\\travel\\backend\\src\\services\\activity.service.ts", "source_location": "L45"}, {"caller_nid": "services_activity_service_activityservice_delete", "callee": "eq", "is_member_call": true, "source_file": "C:\\Users\\Admin\\Desktop\\travel\\backend\\src\\services\\activity.service.ts", "source_location": "L56"}, {"caller_nid": "services_activity_service_activityservice_delete", "callee": "from", "is_member_call": true, "source_file": "C:\\Users\\Admin\\Desktop\\travel\\backend\\src\\services\\activity.service.ts", "source_location": "L56"}]}