{"nodes": [{"id": "c_users_admin_desktop_travel_frontend_src_components_documenttitle_tsx", "label": "DocumentTitle.tsx", "file_type": "code", "source_file": "C:\\Users\\Admin\\Desktop\\travel\\frontend\\src\\components\\DocumentTitle.tsx", "source_location": "L1"}, {"id": "components_documenttitle_documenttitle", "label": "DocumentTitle()", "file_type": "code", "source_file": "C:\\Users\\Admin\\Desktop\\travel\\frontend\\src\\components\\DocumentTitle.tsx", "source_location": "L25"}], "edges": [{"source": "c_users_admin_desktop_travel_frontend_src_components_documenttitle_tsx", "target": "react", "relation": "imports_from", "confidence": "EXTRACTED", "source_file": "C:\\Users\\Admin\\Desktop\\travel\\frontend\\src\\components\\DocumentTitle.tsx", "source_location": "L1", "weight": 1.0}, {"source": "c_users_admin_desktop_travel_frontend_src_components_documenttitle_tsx", "target": "react_router_dom", "relation": "imports_from", "confidence": "EXTRACTED", "source_file": "C:\\Users\\Admin\\Desktop\\travel\\frontend\\src\\components\\DocumentTitle.tsx", "source_location": "L2", "weight": 1.0}, {"source": "c_users_admin_desktop_travel_frontend_src_components_documenttitle_tsx", "target": "components_documenttitle_documenttitle", "relation": "contains", "confidence": "EXTRACTED", "source_file": "C:\\Users\\Admin\\Desktop\\travel\\frontend\\src\\components\\DocumentTitle.tsx", "source_location": "L25", "weight": 1.0}], "raw_calls": [{"caller_nid": "components_documenttitle_documenttitle", "callee": "useLocation", "is_member_call": false, "source_file": "C:\\Users\\Admin\\Desktop\\travel\\frontend\\src\\components\\DocumentTitle.tsx", "source_location": "L26"}, {"caller_nid": "components_documenttitle_documenttitle", "callee": "useEffect", "is_member_call": false, "source_file": "C:\\Users\\Admin\\Desktop\\travel\\frontend\\src\\components\\DocumentTitle.tsx", "source_location": "L28"}]}