{"nodes": [{"id": "c_users_admin_desktop_travel_frontend_src_pages_notes_tsx", "label": "Notes.tsx", "file_type": "code", "source_file": "C:\\Users\\Admin\\Desktop\\travel\\frontend\\src\\pages\\Notes.tsx", "source_location": "L1"}, {"id": "pages_notes_run", "label": "run()", "file_type": "code", "source_file": "C:\\Users\\Admin\\Desktop\\travel\\frontend\\src\\pages\\Notes.tsx", "source_location": "L59"}, {"id": "pages_notes_opencreatemodal", "label": "openCreateModal()", "file_type": "code", "source_file": "C:\\Users\\Admin\\Desktop\\travel\\frontend\\src\\pages\\Notes.tsx", "source_location": "L111"}, {"id": "pages_notes_openeditmodal", "label": "openEditModal()", "file_type": "code", "source_file": "C:\\Users\\Admin\\Desktop\\travel\\frontend\\src\\pages\\Notes.tsx", "source_location": "L117"}, {"id": "pages_notes_closemodal", "label": "closeModal()", "file_type": "code", "source_file": "C:\\Users\\Admin\\Desktop\\travel\\frontend\\src\\pages\\Notes.tsx", "source_location": "L126"}, {"id": "pages_notes_handlesubmit", "label": "handleSubmit()", "file_type": "code", "source_file": "C:\\Users\\Admin\\Desktop\\travel\\frontend\\src\\pages\\Notes.tsx", "source_location": "L132"}, {"id": "pages_notes_handledelete", "label": "handleDelete()", "file_type": "code", "source_file": "C:\\Users\\Admin\\Desktop\\travel\\frontend\\src\\pages\\Notes.tsx", "source_location": "L159"}], "edges": [{"source": "c_users_admin_desktop_travel_frontend_src_pages_notes_tsx", "target": "react", "relation": "imports_from", "confidence": "EXTRACTED", "source_file": "C:\\Users\\Admin\\Desktop\\travel\\frontend\\src\\pages\\Notes.tsx", "source_location": "L1", "weight": 1.0}, {"source": "c_users_admin_desktop_travel_frontend_src_pages_notes_tsx", "target": "lucide_react", "relation": "imports_from", "confidence": "EXTRACTED", "source_file": "C:\\Users\\Admin\\Desktop\\travel\\frontend\\src\\pages\\Notes.tsx", "source_location": "L2", "weight": 1.0}, {"source": "c_users_admin_desktop_travel_frontend_src_pages_notes_tsx", "target": "c_users_admin_desktop_travel_frontend_src_services_note_service", "relation": "imports_from", "confidence": "EXTRACTED", "source_file": "C:\\Users\\Admin\\Desktop\\travel\\frontend\\src\\pages\\Notes.tsx", "source_location": "L12", "weight": 1.0}, {"source": "c_users_admin_desktop_travel_frontend_src_pages_notes_tsx", "target": "c_users_admin_desktop_travel_frontend_src_store_tripstore", "relation": "imports_from", "confidence": "EXTRACTED", "source_file": "C:\\Users\\Admin\\Desktop\\travel\\frontend\\src\\pages\\Notes.tsx", "source_location": "L13", "weight": 1.0}, {"source": "c_users_admin_desktop_travel_frontend_src_pages_notes_tsx", "target": "c_users_admin_desktop_travel_frontend_src_utils_dateutils", "relation": "imports_from", "confidence": "EXTRACTED", "source_file": "C:\\Users\\Admin\\Desktop\\travel\\frontend\\src\\pages\\Notes.tsx", "source_location": "L14", "weight": 1.0}, {"source": "c_users_admin_desktop_travel_frontend_src_pages_notes_tsx", "target": "pages_notes_run", "relation": "contains", "confidence": "EXTRACTED", "source_file": "C:\\Users\\Admin\\Desktop\\travel\\frontend\\src\\pages\\Notes.tsx", "source_location": "L59", "weight": 1.0}, {"source": "c_users_admin_desktop_travel_frontend_src_pages_notes_tsx", "target": "pages_notes_opencreatemodal", "relation": "contains", "confidence": "EXTRACTED", "source_file": "C:\\Users\\Admin\\Desktop\\travel\\frontend\\src\\pages\\Notes.tsx", "source_location": "L111", "weight": 1.0}, {"source": "c_users_admin_desktop_travel_frontend_src_pages_notes_tsx", "target": "pages_notes_openeditmodal", "relation": "contains", "confidence": "EXTRACTED", "source_file": "C:\\Users\\Admin\\Desktop\\travel\\frontend\\src\\pages\\Notes.tsx", "source_location": "L117", "weight": 1.0}, {"source": "c_users_admin_desktop_travel_frontend_src_pages_notes_tsx", "target": "pages_notes_closemodal", "relation": "contains", "confidence": "EXTRACTED", "source_file": "C:\\Users\\Admin\\Desktop\\travel\\frontend\\src\\pages\\Notes.tsx", "source_location": "L126", "weight": 1.0}, {"source": "c_users_admin_desktop_travel_frontend_src_pages_notes_tsx", "target": "pages_notes_handlesubmit", "relation": "contains", "confidence": "EXTRACTED", "source_file": "C:\\Users\\Admin\\Desktop\\travel\\frontend\\src\\pages\\Notes.tsx", "source_location": "L132", "weight": 1.0}, {"source": "c_users_admin_desktop_travel_frontend_src_pages_notes_tsx", "target": "pages_notes_handledelete", "relation": "contains", "confidence": "EXTRACTED", "source_file": "C:\\Users\\Admin\\Desktop\\travel\\frontend\\src\\pages\\Notes.tsx", "source_location": "L159", "weight": 1.0}, {"source": "pages_notes_handlesubmit", "target": "pages_notes_closemodal", "relation": "calls", "confidence": "EXTRACTED", "source_file": "C:\\Users\\Admin\\Desktop\\travel\\frontend\\src\\pages\\Notes.tsx", "source_location": "L151", "weight": 1.0}], "raw_calls": [{"caller_nid": "pages_notes_run", "callee": "setLoading", "is_member_call": false, "source_file": "C:\\Users\\Admin\\Desktop\\travel\\frontend\\src\\pages\\Notes.tsx", "source_location": "L60"}, {"caller_nid": "pages_notes_run", "callee": "getNotes", "is_member_call": true, "source_file": "C:\\Users\\Admin\\Desktop\\travel\\frontend\\src\\pages\\Notes.tsx", "source_location": "L62"}, {"caller_nid": "pages_notes_run", "callee": "setNotes", "is_member_call": false, "source_file": "C:\\Users\\Admin\\Desktop\\travel\\frontend\\src\\pages\\Notes.tsx", "source_location": "L63"}, {"caller_nid": "pages_notes_run", "callee": "error", "is_member_call": true, "source_file": "C:\\Users\\Admin\\Desktop\\travel\\frontend\\src\\pages\\Notes.tsx", "source_location": "L65"}, {"caller_nid": "pages_notes_run", "callee": "setLoading", "is_member_call": false, "source_file": "C:\\Users\\Admin\\Desktop\\travel\\frontend\\src\\pages\\Notes.tsx", "source_location": "L67"}, {"caller_nid": "pages_notes_opencreatemodal", "callee": "setEditingNoteId", "is_member_call": false, "source_file": "C:\\Users\\Admin\\Desktop\\travel\\frontend\\src\\pages\\Notes.tsx", "source_location": "L112"}, {"caller_nid": "pages_notes_opencreatemodal", "callee": "setFormData", "is_member_call": false, "source_file": "C:\\Users\\Admin\\Desktop\\travel\\frontend\\src\\pages\\Notes.tsx", "source_location": "L113"}, {"caller_nid": "pages_notes_opencreatemodal", "callee": "setShowModal", "is_member_call": false, "source_file": "C:\\Users\\Admin\\Desktop\\travel\\frontend\\src\\pages\\Notes.tsx", "source_location": "L114"}, {"caller_nid": "pages_notes_openeditmodal", "callee": "setEditingNoteId", "is_member_call": false, "source_file": "C:\\Users\\Admin\\Desktop\\travel\\frontend\\src\\pages\\Notes.tsx", "source_location": "L118"}, {"caller_nid": "pages_notes_openeditmodal", "callee": "setFormData", "is_member_call": false, "source_file": "C:\\Users\\Admin\\Desktop\\travel\\frontend\\src\\pages\\Notes.tsx", "source_location": "L119"}, {"caller_nid": "pages_notes_openeditmodal", "callee": "setShowModal", "is_member_call": false, "source_file": "C:\\Users\\Admin\\Desktop\\travel\\frontend\\src\\pages\\Notes.tsx", "source_location": "L123"}, {"caller_nid": "pages_notes_closemodal", "callee": "setShowModal", "is_member_call": false, "source_file": "C:\\Users\\Admin\\Desktop\\travel\\frontend\\src\\pages\\Notes.tsx", "source_location": "L127"}, {"caller_nid": "pages_notes_closemodal", "callee": "setEditingNoteId", "is_member_call": false, "source_file": "C:\\Users\\Admin\\Desktop\\travel\\frontend\\src\\pages\\Notes.tsx", "source_location": "L128"}, {"caller_nid": "pages_notes_closemodal", "callee": "setFormData", "is_member_call": false, "source_file": "C:\\Users\\Admin\\Desktop\\travel\\frontend\\src\\pages\\Notes.tsx", "source_location": "L129"}, {"caller_nid": "pages_notes_handlesubmit", "callee": "preventDefault", "is_member_call": true, "source_file": "C:\\Users\\Admin\\Desktop\\travel\\frontend\\src\\pages\\Notes.tsx", "source_location": "L133"}, {"caller_nid": "pages_notes_handlesubmit", "callee": "trim", "is_member_call": true, "source_file": "C:\\Users\\Admin\\Desktop\\travel\\frontend\\src\\pages\\Notes.tsx", "source_location": "L134"}, {"caller_nid": "pages_notes_handlesubmit", "callee": "setSubmitting", "is_member_call": false, "source_file": "C:\\Users\\Admin\\Desktop\\travel\\frontend\\src\\pages\\Notes.tsx", "source_location": "L136"}, {"caller_nid": "pages_notes_handlesubmit", "callee": "updateNote", "is_member_call": true, "source_file": "C:\\Users\\Admin\\Desktop\\travel\\frontend\\src\\pages\\Notes.tsx", "source_location": "L139"}, {"caller_nid": "pages_notes_handlesubmit", "callee": "trim", "is_member_call": true, "source_file": "C:\\Users\\Admin\\Desktop\\travel\\frontend\\src\\pages\\Notes.tsx", "source_location": "L140"}, {"caller_nid": "pages_notes_handlesubmit", "callee": "trim", "is_member_call": true, "source_file": "C:\\Users\\Admin\\Desktop\\travel\\frontend\\src\\pages\\Notes.tsx", "source_location": "L141"}, {"caller_nid": "pages_notes_handlesubmit", "callee": "setNotes", "is_member_call": false, "source_file": "C:\\Users\\Admin\\Desktop\\travel\\frontend\\src\\pages\\Notes.tsx", "source_location": "L143"}, {"caller_nid": "pages_notes_handlesubmit", "callee": "createNote", "is_member_call": true, "source_file": "C:\\Users\\Admin\\Desktop\\travel\\frontend\\src\\pages\\Notes.tsx", "source_location": "L145"}, {"caller_nid": "pages_notes_handlesubmit", "callee": "trim", "is_member_call": true, "source_file": "C:\\Users\\Admin\\Desktop\\travel\\frontend\\src\\pages\\Notes.tsx", "source_location": "L146"}, {"caller_nid": "pages_notes_handlesubmit", "callee": "trim", "is_member_call": true, "source_file": "C:\\Users\\Admin\\Desktop\\travel\\frontend\\src\\pages\\Notes.tsx", "source_location": "L147"}, {"caller_nid": "pages_notes_handlesubmit", "callee": "setNotes", "is_member_call": false, "source_file": "C:\\Users\\Admin\\Desktop\\travel\\frontend\\src\\pages\\Notes.tsx", "source_location": "L149"}, {"caller_nid": "pages_notes_handlesubmit", "callee": "alert", "is_member_call": false, "source_file": "C:\\Users\\Admin\\Desktop\\travel\\frontend\\src\\pages\\Notes.tsx", "source_location": "L153"}, {"caller_nid": "pages_notes_handlesubmit", "callee": "setSubmitting", "is_member_call": false, "source_file": "C:\\Users\\Admin\\Desktop\\travel\\frontend\\src\\pages\\Notes.tsx", "source_location": "L155"}, {"caller_nid": "pages_notes_handledelete", "callee": "confirm", "is_member_call": false, "source_file": "C:\\Users\\Admin\\Desktop\\travel\\frontend\\src\\pages\\Notes.tsx", "source_location": "L161"}, {"caller_nid": "pages_notes_handledelete", "callee": "deleteNote", "is_member_call": true, "source_file": "C:\\Users\\Admin\\Desktop\\travel\\frontend\\src\\pages\\Notes.tsx", "source_location": "L164"}, {"caller_nid": "pages_notes_handledelete", "callee": "setNotes", "is_member_call": false, "source_file": "C:\\Users\\Admin\\Desktop\\travel\\frontend\\src\\pages\\Notes.tsx", "source_location": "L165"}, {"caller_nid": "pages_notes_handledelete", "callee": "alert", "is_member_call": false, "source_file": "C:\\Users\\Admin\\Desktop\\travel\\frontend\\src\\pages\\Notes.tsx", "source_location": "L167"}]}